odoo9_addon_pos_empty_home-9.0.1.0.0-py2.7-nspkg.pth
odoo9_addon_pos_empty_home-9.0.1.0.0.dist-info/DESCRIPTION.rst
odoo9_addon_pos_empty_home-9.0.1.0.0.dist-info/METADATA
odoo9_addon_pos_empty_home-9.0.1.0.0.dist-info/RECORD
odoo9_addon_pos_empty_home-9.0.1.0.0.dist-info/WHEEL
odoo9_addon_pos_empty_home-9.0.1.0.0.dist-info/metadata.json
odoo9_addon_pos_empty_home-9.0.1.0.0.dist-info/namespace_packages.txt
odoo9_addon_pos_empty_home-9.0.1.0.0.dist-info/top_level.txt
odoo_addons/pos_empty_home/README.rst
odoo_addons/pos_empty_home/__init__.py
odoo_addons/pos_empty_home/__openerp__.py
odoo_addons/pos_empty_home/i18n/fr.po
odoo_addons/pos_empty_home/static/description/icon.png
odoo_addons/pos_empty_home/static/description/pos_empty_home.png
odoo_addons/pos_empty_home/static/src/css/pos_empty_home.css
odoo_addons/pos_empty_home/static/src/js/db.js
odoo_addons/pos_empty_home/static/src/js/screens.js
odoo_addons/pos_empty_home/static/src/xml/pos_empty_home.xml
odoo_addons/pos_empty_home/static/src/xml/templates.xml
