Metadata-Version: 2.0
Name: odoo9-addon-pos-empty-home
Version: 9.0.1.0.0
Summary: Hide products at the start of the Point of Sale
Home-page: http://www.lalouve.net/
Author: La Louve, GRAP, Odoo Community Association (OCA)
Author-email: support@odoo-community.org
License: AGPL-3
Platform: UNKNOWN
Classifier: Programming Language :: Python :: 2.7
Classifier: Framework :: Odoo
Classifier: License :: OSI Approved :: GNU Affero General Public License v3
Requires-Dist: odoo (<9.1a,>=9.0a)
